yamlfu/__init__.py
yamlfu/__main__.py
yamlfu/cli.py
yamlfu/functions.py
yamlfu/loader.py
yamlfu/pretty.py
yamlfu/tests/test_files.py
yamlfu-0.1.0.dist-info/LICENSE
yamlfu-0.1.0.dist-info/METADATA
yamlfu-0.1.0.dist-info/WHEEL
yamlfu-0.1.0.dist-info/entry_points.txt
yamlfu-0.1.0.dist-info/top_level.txt
yamlfu-0.1.0.dist-info/RECORD
