Metadata-Version: 2.1
Name: yamlfu
Version: 0.1.0
Summary: Create the skeleton for a python package/project
Home-page: https://github.com/joaompinto/yamlfu
Author: João Pinto
Author-email: lamego.pinto@gmail.com
License: MIT
Platform: UNKNOWN
Requires-Dist: dinterpol
Requires-Dist: pyyaml
Requires-Dist: pygments
